batch_downloader/__init__.py
batch_downloader/async_batch_downloader.py
batch_downloader/base_downloader.py
batch_downloader/batch_downloader.py
tests/__init__.py
tests/test_async_downloader.py
tests/test_downloader.py
batch_downloader-0.1.2.dist-info/LICENSE
batch_downloader-0.1.2.dist-info/METADATA
batch_downloader-0.1.2.dist-info/WHEEL
batch_downloader-0.1.2.dist-info/top_level.txt
batch_downloader-0.1.2.dist-info/RECORD
