Metadata-Version: 2.2
Name: batch_downloader
Version: 0.1.2
Summary: A simple batch downloader with chunked downloads
Home-page: https://github.com/Zzhenping/batch_downloader
Author: zhenpingzhan
Author-email: stallzhan@gmail.com
Classifier: Programming Language :: Python :: 3
Classifier: License :: OSI Approved :: MIT License
Classifier: Operating System :: OS Independent
Requires-Python: >=3.8
License-File: LICENSE
Requires-Dist: requests>=2.25.1
Requires-Dist: aiohttp>=3.8.0
Dynamic: author
Dynamic: author-email
Dynamic: classifier
Dynamic: description
Dynamic: description-content-type
Dynamic: home-page
Dynamic: requires-dist
Dynamic: requires-python
Dynamic: summary
